AUTHORS
CHANGES.rst
LICENSE
MANIFEST.in
README.rst
setup.cfg
setup.py
pyodesys/__init__.py
pyodesys/_release.py
pyodesys/analysis.py
pyodesys/convergence.py
pyodesys/core.py
pyodesys/integrators.py
pyodesys/plotting.py
pyodesys/results.py
pyodesys/symbolic.py
pyodesys/util.py
pyodesys.egg-info/PKG-INFO
pyodesys.egg-info/SOURCES.txt
pyodesys.egg-info/dependency_links.txt
pyodesys.egg-info/requires.txt
pyodesys.egg-info/top_level.txt
pyodesys/native/__init__.py
pyodesys/native/_base.py
pyodesys/native/cvode.py
pyodesys/native/gsl.py
pyodesys/native/odeint.py
pyodesys/native/util.py
pyodesys/native/sources/_cvode_wrapper.pyx
pyodesys/native/sources/_gsl_wrapper.pyx
pyodesys/native/sources/_odeint_wrapper.pyx
pyodesys/native/sources/anyode.pxd
pyodesys/native/sources/odesys_anyode.hpp
pyodesys/native/sources/odesys_anyode.pxd
pyodesys/native/sources/odesys_anyode_iterative.hpp
pyodesys/native/sources/odesys_anyode_iterative.pxd
pyodesys/native/sources/odesys_anyode_template.cpp
pyodesys/native/sources/odesys_util.hpp
pyodesys/native/sources/odesys_util.pxd
pyodesys/native/sources/standalone_template.cpp
pyodesys/native/tests/__init__.py
pyodesys/native/tests/_test_robertson_native.py
pyodesys/native/tests/_tests.py
pyodesys/native/tests/test_cvode.py
pyodesys/native/tests/test_gsl.py
pyodesys/native/tests/test_odeint.py
pyodesys/tests/__init__.py
pyodesys/tests/_cetsa.py
pyodesys/tests/_robertson.py
pyodesys/tests/bateman.py
pyodesys/tests/test_core.py
pyodesys/tests/test_plotting.py
pyodesys/tests/test_results.py
pyodesys/tests/test_robertson.py
pyodesys/tests/test_symbolic.py
pyodesys/tests/test_util.py