Metadata-Version: 2.1
Name: pyodesys
Version: 0.14.3
Summary: Straightforward numerical integration of ODE systems from Python.
Home-page: https://github.com/bjodah/pyodesys
Author: Bjoern I. Dahlgren 
Author-email: bjodah@gmail.com
License: BSD
Classifier: Development Status :: 4 - Beta
Classifier: License :: OSI Approved :: BSD License
Classifier: Operating System :: OS Independent
Classifier: Topic :: Scientific/Engineering
Classifier: Topic :: Scientific/Engineering :: Mathematics
Classifier: Programming Language :: Python :: 3.7
Classifier: Programming Language :: Python :: 3.8
Requires-Python: >=3.7
Provides-Extra: all
Provides-Extra: docs
Provides-Extra: integrators
Provides-Extra: native
Provides-Extra: testing
License-File: LICENSE
License-File: AUTHORS
